networking_ofagent/__init__.py
networking_ofagent/hooks.py
networking_ofagent/i18n.py
networking_ofagent/hacking/__init__.py
networking_ofagent/hacking/checks.py
networking_ofagent/plugins/__init__.py
networking_ofagent/plugins/ml2/__init__.py
networking_ofagent/plugins/ml2/drivers/__init__.py
networking_ofagent/plugins/ml2/drivers/mech_ofagent.py
networking_ofagent/plugins/ofagent/__init__.py
networking_ofagent/plugins/ofagent/agent/__init__.py
networking_ofagent/plugins/ofagent/agent/arp_lib.py
networking_ofagent/plugins/ofagent/agent/constants.py
networking_ofagent/plugins/ofagent/agent/flows.py
networking_ofagent/plugins/ofagent/agent/main.py
networking_ofagent/plugins/ofagent/agent/metadata.py
networking_ofagent/plugins/ofagent/agent/monitor.py
networking_ofagent/plugins/ofagent/agent/ofa_neutron_agent.py
networking_ofagent/plugins/ofagent/agent/ofswitch.py
networking_ofagent/plugins/ofagent/agent/ports.py
networking_ofagent/plugins/ofagent/agent/tables.py
networking_ofagent/plugins/ofagent/common/__init__.py
networking_ofagent/plugins/ofagent/common/config.py
networking_ofagent/tests/__init__.py
networking_ofagent/tests/unit/__init__.py
networking_ofagent/tests/unit/ml2/__init__.py
networking_ofagent/tests/unit/ml2/drivers/__init__.py
networking_ofagent/tests/unit/ml2/drivers/test_ofagent_mech.py
networking_ofagent/tests/unit/ofagent/__init__.py
networking_ofagent/tests/unit/ofagent/fake_oflib.py
networking_ofagent/tests/unit/ofagent/ofa_test_base.py
networking_ofagent/tests/unit/ofagent/test_arp_lib.py
networking_ofagent/tests/unit/ofagent/test_monitor.py
networking_ofagent/tests/unit/ofagent/test_ofa_flows.py
networking_ofagent/tests/unit/ofagent/test_ofa_neutron_agent.py
networking_ofagent/tests/unit/ofagent/test_ofa_ports.py
networking_ofagent/tests/unit/ofagent/test_ofswitch.py
networking_ofagent-2015.1.6.data/data/etc/neutron/plugins/ml2/ml2_conf_ofa.ini
networking_ofagent-2015.1.6.dist-info/DESCRIPTION.rst
networking_ofagent-2015.1.6.dist-info/METADATA
networking_ofagent-2015.1.6.dist-info/RECORD
networking_ofagent-2015.1.6.dist-info/WHEEL
networking_ofagent-2015.1.6.dist-info/entry_points.txt
networking_ofagent-2015.1.6.dist-info/metadata.json
networking_ofagent-2015.1.6.dist-info/pbr.json
networking_ofagent-2015.1.6.dist-info/top_level.txt
