Metadata-Version: 2.0
Name: networking-ofagent
Version: 2015.1.6
Summary: OpenStack Networking ofagent
Home-page: https://wiki.openstack.org/wiki/Neutron/OFAgent
Author: Ryu Team
Author-email: ryu-devel@lists.sourceforge.net
License: Apache License 2.0
Platform: Any
Classifier: Environment :: OpenStack
Classifier: Intended Audience :: Information Technology
Classifier: Intended Audience :: System Administrators
Classifier: License :: OSI Approved :: Apache Software License
Classifier: Operating System :: POSIX :: Linux
Classifier: Programming Language :: Python
Classifier: Programming Language :: Python :: 2
Classifier: Programming Language :: Python :: 2.7
Requires-Dist: Babel (>=1.3)
Requires-Dist: oslo.config (<1.10.0,>=1.9.3)
Requires-Dist: oslo.i18n (<1.6.0,>=1.5.0)
Requires-Dist: oslo.log (<1.1.0,>=1.0.0)
Requires-Dist: oslo.messaging (<1.9.0,>=1.8.0)
Requires-Dist: oslo.utils (<1.5.0,>=1.4.0)
Requires-Dist: pbr (<1.0,>=0.6,!=0.7)
Requires-Dist: ryu (>=3.19)
Requires-Dist: stevedore (<1.4.0,>=1.3.0)
